MANIFEST.in
README.rst
setup.py
cs/__init__.py
cs.auth.facebook.egg-info/PKG-INFO
cs.auth.facebook.egg-info/SOURCES.txt
cs.auth.facebook.egg-info/dependency_links.txt
cs.auth.facebook.egg-info/entry_points.txt
cs.auth.facebook.egg-info/namespace_packages.txt
cs.auth.facebook.egg-info/not-zip-safe
cs.auth.facebook.egg-info/requires.txt
cs.auth.facebook.egg-info/top_level.txt
cs/auth/__init__.py
cs/auth/facebook/__init__.py
cs/auth/facebook/addform.pt
cs/auth/facebook/browser.py
cs/auth/facebook/configure.zcml
cs/auth/facebook/controlpanel.py
cs/auth/facebook/interfaces.py
cs/auth/facebook/login.py
cs/auth/facebook/plugin.py
cs/auth/facebook/rebuild_i18n.sh
cs/auth/facebook/setuphandlers.py
cs/auth/facebook/tests.py
cs/auth/facebook/user.py
cs/auth/facebook/locales/cs.auth.facebook-manual.pot
cs/auth/facebook/locales/cs.auth.facebook.pot
cs/auth/facebook/locales/de/LC_MESSAGES/cs.auth.facebook.po
cs/auth/facebook/locales/es/LC_MESSAGES/cs.auth.facebook.po
cs/auth/facebook/locales/eu/LC_MESSAGES/cs.auth.facebook.po
cs/auth/facebook/profiles/default/actions.xml
cs/auth/facebook/profiles/default/browserlayer.xml
cs/auth/facebook/profiles/default/controlpanel.xml
cs/auth/facebook/profiles/default/cs.auth.facebook-various.txt
cs/auth/facebook/profiles/default/metadata.xml
cs/auth/facebook/profiles/default/registry.xml
cs/auth/facebook/templates/facebooklogin_viewlet.pt
docs/HISTORY.txt
docs/INSTALL.txt
docs/LICENSE.GPL
docs/LICENSE.txt