Metadata-Version: 1.1
Name: cs.auth.facebook
Version: 1.2
Summary: Facebook authentication plugin for Plone
Home-page: https://github.com/codesyntax/cs.auth.facebook
Author: Mikel Larreategi
Author-email: mlarreategi@codesyntax.com
License: GPL
Keywords: plone pas login facebook authentication
Platform: UNKNOWN
Classifier: Framework :: Plone
Classifier: Programming Language :: Python
